requestxxm/__init__.py
requestxxm/main.py
requestxxm-0.6.2.dist-info/METADATA
requestxxm-0.6.2.dist-info/WHEEL
requestxxm-0.6.2.dist-info/licenses/LICENSE
requestxxm-0.6.2.dist-info/RECORD
