Metadata-Version: 2.1
Name: requestxxm
Version: 0.6.2
Summary: requestxxm
Project-URL: Homepage, https://github.com/jarvan1/requestxxm
Project-URL: Issues, https://github.com/jarvan1/requestxxm/issues
Author-email: "xinming.xu" <xu_xinming@live.com>
License-File: LICENSE
Classifier: License :: OSI Approved :: MIT License
Classifier: Operating System :: OS Independent
Classifier: Programming Language :: Python :: 3
Requires-Python: >=3.8
